fftpower23.py
fftpower23-1.0.0.dist-info/METADATA
fftpower23-1.0.0.dist-info/RECORD
fftpower23-1.0.0.dist-info/WHEEL
fftpower23-1.0.0.dist-info/top_level.txt
