Metadata-Version: 2.1
Name: fftpower23
Version: 1.0.0
Summary: Fast Fourier Transformation with powers 2 and 3
Home-page: https://bitbucket.org/VladimirPopov43/fft_python/src
Author: Vladimir Popov
Author-email: vladimir.popov@gmx.com
License: UNKNOWN
Platform: UNKNOWN
Classifier: Programming Language :: Python
Classifier: License :: OSI Approved :: MIT License
Classifier: Operating System :: OS Independent
